cnapps/CN_yield_prediction.py
cnapps/__init__.py
cnapps-0.0.1.dist-info/LICENSE.txt
cnapps-0.0.1.dist-info/METADATA
cnapps-0.0.1.dist-info/WHEEL
cnapps-0.0.1.dist-info/top_level.txt
cnapps-0.0.1.dist-info/RECORD
